geeup/__init__.py
geeup/__main__.py
geeup/auth.py
geeup/batch_uploader.py
geeup/geeup.py
geeup/metadata_loader.py
geeup/quota.py
geeup/tasks.py
geeup/tuploader.py
geeup/zip_shape.py
geeup-2.0.0.dist-info/licenses/LICENSE
geeup-2.0.0.dist-info/METADATA
geeup-2.0.0.dist-info/WHEEL
geeup-2.0.0.dist-info/entry_points.txt
geeup-2.0.0.dist-info/top_level.txt
geeup-2.0.0.dist-info/RECORD
