Metadata-Version: 2.4
Name: geeup
Version: 2.0.0
Summary: Simple Client for Earth Engine Uploads
Author-email: Samapriya Roy <samapriya.roy@gmail.com>
License-Expression: Apache-2.0
Project-URL: Homepage, https://github.com/samapriya/geeup
Project-URL: Documentation, https://geeup.geetools.xyz/
Project-URL: Repository, https://github.com/samapriya/geeup
Project-URL: Issues, https://github.com/samapriya/geeup/issues
Keywords: earth engine,gee,upload,raster,vector,geospatial
Classifier: Development Status :: 6 - Mature
Classifier: Intended Audience :: Developers
Classifier: Intended Audience :: Science/Research
Classifier: Natural Language :: English
Classifier: Programming Language :: Python :: 3
Classifier: Programming Language :: Python :: 3.10
Classifier: Programming Language :: Python :: 3.11
Classifier: Programming Language :: Python :: 3.12
Classifier: Operating System :: OS Independent
Classifier: Topic :: Scientific/Engineering :: GIS
Requires-Python: >=3.10
License-File: LICENSE
Requires-Dist: earthengine-api>=0.1.370
Requires-Dist: requests>=2.31.0
Requires-Dist: requests-toolbelt>=1.0.0
Requires-Dist: urllib3>=2.0.0
Requires-Dist: pydantic>=2.0.0
Requires-Dist: rich>=13.0.0
Requires-Dist: tqdm>=4.65.0
Requires-Dist: packaging>=23.0
Provides-Extra: dev
Requires-Dist: pytest>=7.0.0; extra == "dev"
Requires-Dist: pytest-cov>=4.0.0; extra == "dev"
Requires-Dist: black>=23.0.0; extra == "dev"
Requires-Dist: ruff>=0.1.0; extra == "dev"
Dynamic: license-file
